femtomat/TA.py
femtomat/__init__.py
femtomat/functions.py
femtomat-0.2.10.dist-info/LICENCE.txt
femtomat-0.2.10.dist-info/METADATA
femtomat-0.2.10.dist-info/WHEEL
femtomat-0.2.10.dist-info/top_level.txt
femtomat-0.2.10.dist-info/RECORD
