Metadata-Version: 2.1
Name: femtomat
Version: 0.2.10
Summary: General analysis tools for Femtomat group of Natalie Banerji
Home-page: https://github.com/GarethJMoore/femtomat_Package
Author: Gareth Moore
Author-email: garethjohnmoore01@gmail.com
Project-URL: Bug Tracker, https://github.com/GarethJMoore/femtomat_Package/issues
Classifier: Programming Language :: Python :: 3
Classifier: License :: OSI Approved :: MIT License
Classifier: Operating System :: OS Independent
Requires-Python: >=3.6
License-File: LICENCE.txt
